UDPComms/UDPComms.py
UDPComms/__init__.py
UDPComms/version.py
UDPComms-2.1.1.dist-info/LICENSE.md
UDPComms-2.1.1.dist-info/METADATA
UDPComms-2.1.1.dist-info/WHEEL
UDPComms-2.1.1.dist-info/top_level.txt
UDPComms-2.1.1.dist-info/RECORD
