Metadata-Version: 2.1
Name: UDPComms
Version: 2.1.1
Summary: Simple library for sending messages over UDP
Home-page: https://github.com/stanfordroboticsclub/UDP-Comms
Author: Michal Adamkiewicz
Author-email: mikadam@stanford.edu
License: MIT
Platform: UNKNOWN
